{
  "info": {
    "name": "KismatX API Collection",
    "description": "Comprehensive RBAC-based Gaming Platform API with Demo Data",
    "version": "1.0.0",
    "schema": "https://schema.getpostman.com/json/collection/v2.1.0/collection.json"
  },
  "auth": {
    "type": "bearer",
    "bearer": [
      {
        "key": "token",
        "value": "{{accessToken}}",
        "type": "string"
      }
    ]
  },
  "variable": [
    {
      "key": "baseUrl",
      "value": "http://localhost:5001",
      "type": "string"
    },
    {
      "key": "accessToken",
      "value": "",
      "type": "string"
    },
    {
      "key": "refreshToken",
      "value": "",
      "type": "string"
    },
    {
      "key": "userId",
      "value": "",
      "type": "string"
    },
    {
      "key": "adminToken",
      "value": "",
      "type": "string"
    }
  ],
  "item": [
    {
      "name": "🔐 Authentication",
      "description": "Authentication flows for KismatX. Login is restricted to user_id + password only. Register creates a player by default. Use the returned tokens for protected routes.",
      "item": [
        {
          "name": "Register Player",
          "description": "Register a Player. Requires deposit_amount. profile_pic optional.",
          "request": {
            "method": "POST",
            "header": [
              {
                "key": "Content-Type",
                "value": "application/json"
              }
            ],
            "body": {
              "mode": "raw",
              "raw": "{\n  \"user_id\": \"player001\",\n  \"first_name\": \"John\",\n  \"last_name\": \"Doe\",\n  \"email\": \"john.doe@example.com\",\n  \"mobile\": \"1234567890\",\n  \"password\": \"password123\",\n  \"user_type\": \"player\",\n  \"deposit_amount\": 250.50,\n  \"profile_pic\": null,\n  \"alternate_mobile\": \"9876543210\",\n  \"address\": \"123 Gaming Street\",\n  \"city\": \"Mumbai\",\n  \"state\": \"Maharashtra\",\n  \"pin_code\": \"400001\",\n  \"region\": \"West\"\n}"
            },
            "url": {
              "raw": "{{baseUrl}}/api/auth/register",
              "host": ["{{baseUrl}}"],
              "path": ["api", "auth", "register"]
            }
          }
        },
        {
          "name": "Register Admin",
          "description": "Register an Admin. deposit_amount ignored, profile_pic optional.",
          "request": {
            "method": "POST",
            "header": [
              {
                "key": "Content-Type",
                "value": "application/json"
              }
            ],
            "body": {
              "mode": "raw",
              "raw": "{\n  \"user_id\": \"admin001\",\n  \"first_name\": \"Admin\",\n  \"last_name\": \"User\",\n  \"email\": \"admin@kismatx.com\",\n  \"mobile\": \"9876543210\",\n  \"password\": \"admin123\",\n  \"user_type\": \"admin\",\n  \"profile_pic\": null,\n  \"alternate_mobile\": \"1234567890\",\n  \"address\": \"Admin Office\",\n  \"city\": \"Delhi\",\n  \"state\": \"Delhi\",\n  \"pin_code\": \"110001\",\n  \"region\": \"North\"\n}"
            },
            "url": {
              "raw": "{{baseUrl}}/api/auth/register",
              "host": ["{{baseUrl}}"],
              "path": ["api", "auth", "register"]
            }
          }
        },
        {
          "name": "Login Player (user_id)",
          "event": [
            {
              "listen": "test",
              "script": {
                "exec": [
                  "if (pm.response.code === 200) {",
                  "    const response = pm.response.json();",
                  "    pm.collectionVariables.set('accessToken', response.accessToken);",
                  "    pm.collectionVariables.set('refreshToken', response.refreshToken);",
                  "    pm.collectionVariables.set('userId', response.user.id);",
                  "    console.log('Login successful! Token saved.');",
                  "}"
                ] 
              }
            }
          ],
          "request": {
            "method": "POST",
            "header": [
              {
                "key": "Content-Type",
                "value": "application/json"
              }
            ],
            "body": {
              "mode": "raw",
              "raw": "{\n  \"user_id\": \"player001\",\n  \"password\": \"password123\"\n}"
            },
            "url": {
              "raw": "{{baseUrl}}/api/auth/login",
              "host": ["{{baseUrl}}"],
              "path": ["api", "auth", "login"]
            }
          }
        },
        {
          "name": "Login Admin (user_id)",
          "event": [
            {
              "listen": "test",
              "script": {
                "exec": [
                  "if (pm.response.code === 200) {",
                  "    const response = pm.response.json();",
                  "    pm.collectionVariables.set('adminToken', response.accessToken);",
                  "    console.log('Admin login successful! Token saved.');",
                  "}"
                ]
              }
            }
          ],
          "request": {
            "method": "POST",
            "header": [
              {
                "key": "Content-Type",
                "value": "application/json"
              }
            ],
            "body": {
              "mode": "raw",
              "raw": "{\n  \"user_id\": \"admin001\",\n  \"password\": \"admin123\"\n}"
            },
            "url": {
              "raw": "{{baseUrl}}/api/auth/login",
              "host": ["{{baseUrl}}"],
              "path": ["api", "auth", "login"]
            }
          }
        },
        {
          "name": "Logout",
          "request": {
            "method": "POST",
            "header": [
              {
                "key": "Content-Type",
                "value": "application/json"
              }
            ],
            "body": {
              "mode": "raw",
              "raw": "{\n  \"refreshToken\": \"{{refreshToken}}\"\n}"
            },
            "url": {
              "raw": "{{baseUrl}}/api/auth/logout",
              "host": ["{{baseUrl}}"],
              "path": ["api", "auth", "logout"]
            }
          }
        },
        {
          "name": "Refresh Token",
          "request": {
            "method": "POST",
            "header": [
              {
                "key": "Content-Type",
                "value": "application/json"
              }
            ],
            "body": {
              "mode": "raw",
              "raw": "{\n  \"refreshToken\": \"{{refreshToken}}\"\n}"
            },
            "url": {
              "raw": "{{baseUrl}}/api/auth/refresh-token",
              "host": ["{{baseUrl}}"],
              "path": ["api", "auth", "refresh-token"]
            }
          }
        },
        {
          "name": "Forgot Password",
          "request": {
            "method": "POST",
            "header": [
              {
                "key": "Content-Type",
                "value": "application/json"
              }
            ],
            "body": {
              "mode": "raw",
              "raw": "{\n  \"email_or_mobile\": \"john.doe@example.com\"\n}"
            },
            "url": {
              "raw": "{{baseUrl}}/api/auth/forgot-password",
              "host": ["{{baseUrl}}"],
              "path": ["api", "auth", "forgot-password"]
            }
          }
        }
      ]
    },
    {
      "name": "👤 User Management",
      "description": "Endpoints for profile operations. Use the access token from login. Update profile supports address fields and names.",
      "item": [
        {
          "name": "Get My Profile",
          "request": {
            "method": "GET",
            "header": [
              {
                "key": "Authorization",
                "value": "Bearer {{accessToken}}"
              }
            ],
            "url": {
              "raw": "{{baseUrl}}/api/user/profile",
              "host": ["{{baseUrl}}"],
              "path": ["api", "user", "profile"]
            }
          }
        },
        {
          "name": "Update My Profile",
          "request": {
            "method": "PUT",
            "header": [
              {
                "key": "Content-Type",
                "value": "application/json"
              },
              {
                "key": "Authorization",
                "value": "Bearer {{accessToken}}"
              }
            ],
            "body": {
              "mode": "raw",
              "raw": "{\n  \"first_name\": \"John Updated\",\n  \"last_name\": \"Doe Updated\",\n  \"city\": \"Mumbai\",\n  \"state\": \"Maharashtra\",\n  \"pin_code\": \"400001\"\n}"
            },
            "url": {
              "raw": "{{baseUrl}}/api/user/profile",
              "host": ["{{baseUrl}}"],
              "path": ["api", "user", "profile"]
            }
          }
        },
        {
          "name": "Change My Password",
          "request": {
            "method": "POST",
            "header": [
              {
                "key": "Content-Type",
                "value": "application/json"
              },
              {
                "key": "Authorization",
                "value": "Bearer {{accessToken}}"
              }
            ],
            "body": {
              "mode": "raw",
              "raw": "{\n  \"currentPassword\": \"password123\",\n  \"newPassword\": \"newpassword123\"\n}"
            },
            "url": {
              "raw": "{{baseUrl}}/api/user/change-password",
              "host": ["{{baseUrl}}"],
              "path": ["api", "user", "change-password"]
            }
          }
        }
      ]
    },
    {
      "name": "⚙️ Admin Panel",
      "description": "Admin-only endpoints. Requires an access token from an account with Super Admin/Admin role. Includes dashboard, user CRUD, and audit visibility.",
      "item": [
        {
          "name": "Admin Dashboard",
          "request": {
            "method": "GET",
            "header": [
              {
                "key": "Authorization",
                "value": "Bearer {{adminToken}}"
              }
            ],
            "url": {
              "raw": "{{baseUrl}}/api/admin/dashboard",
              "host": ["{{baseUrl}}"],
              "path": ["api", "admin", "dashboard"]
            }
          }
        },
        {
          "name": "Get All Users",
          "request": {
            "method": "GET",
            "header": [
              {
                "key": "Authorization",
                "value": "Bearer {{adminToken}}"
              }
            ],
            "url": {
              "raw": "{{baseUrl}}/api/admin/users?page=1&limit=10&status=active",
              "host": ["{{baseUrl}}"],
              "path": ["api", "admin", "users"],
              "query": [
                {
                  "key": "page",
                  "value": "1"
                },
                {
                  "key": "limit",
                  "value": "10"
                },
                {
                  "key": "status",
                  "value": "active"
                }
              ]
            }
          }
        },
        {
          "name": "Create New User",
          "request": {
            "method": "POST",
            "header": [
              {
                "key": "Content-Type",
                "value": "application/json"
              },
              {
                "key": "Authorization",
                "value": "Bearer {{adminToken}}"
              }
            ],
            "body": {
              "mode": "raw",
              "raw": "{\n  \"user_id\": \"player002\",\n  \"first_name\": \"Jane\",\n  \"last_name\": \"Smith\",\n  \"email\": \"jane.smith@example.com\",\n  \"mobile\": \"9876543211\",\n  \"password\": \"password123\",\n  \"user_type\": \"player\",\n  \"status\": \"active\",\n  \"roles\": [1]\n}"
            },
            "url": {
              "raw": "{{baseUrl}}/api/admin/users",
              "host": ["{{baseUrl}}"],
              "path": ["api", "admin", "users"]
            }
          }
        },
        {
          "name": "Get User by ID",
          "request": {
            "method": "GET",
            "header": [
              {
                "key": "Authorization",
                "value": "Bearer {{adminToken}}"
              }
            ],
            "url": {
              "raw": "{{baseUrl}}/api/admin/users/{{userId}}",
              "host": ["{{baseUrl}}"],
              "path": ["api", "admin", "users", "{{userId}}"]
            }
          }
        },
        {
          "name": "Update User",
          "request": {
            "method": "PUT",
            "header": [
              {
                "key": "Content-Type",
                "value": "application/json"
              },
              {
                "key": "Authorization",
                "value": "Bearer {{adminToken}}"
              }
            ],
            "body": {
              "mode": "raw",
              "raw": "{\n  \"first_name\": \"John Updated\",\n  \"last_name\": \"Doe Updated\",\n  \"status\": \"active\",\n  \"deposit_amount\": 1000.00\n}"
            },
            "url": {
              "raw": "{{baseUrl}}/api/admin/users/{{userId}}",
              "host": ["{{baseUrl}}"],
              "path": ["api", "admin", "users", "{{userId}}"]
            }
          }
        },
        {
          "name": "Change User Status",
          "request": {
            "method": "PUT",
            "header": [
              {
                "key": "Content-Type",
                "value": "application/json"
              },
              {
                "key": "Authorization",
                "value": "Bearer {{adminToken}}"
              }
            ],
            "body": {
              "mode": "raw",
              "raw": "{\n  \"status\": \"banned\"\n}"
            },
            "url": {
              "raw": "{{baseUrl}}/api/admin/users/{{userId}}/status",
              "host": ["{{baseUrl}}"],
              "path": ["api", "admin", "users", "{{userId}}", "status"]
            }
          }
        },
        {
          "name": "Reset User Password",
          "request": {
            "method": "POST",
            "header": [
              {
                "key": "Content-Type",
                "value": "application/json"
              },
              {
                "key": "Authorization",
                "value": "Bearer {{adminToken}}"
              }
            ],
            "body": {
              "mode": "raw",
              "raw": "{\n  \"newPassword\": \"newpassword123\"\n}"
            },
            "url": {
              "raw": "{{baseUrl}}/api/admin/users/{{userId}}/reset-password",
              "host": ["{{baseUrl}}"],
              "path": ["api", "admin", "users", "{{userId}}", "reset-password"]
            }
          }
        },
        {
          "name": "Kill User Sessions (Admin)",
          "description": "Revoke all active sessions (refresh tokens) for a user by user_id. Use when the user is locked out due to single-session policy.",
          "request": {
            "method": "POST",
            "header": [
              { "key": "Authorization", "value": "Bearer {{adminToken}}" },
              { "key": "Content-Type", "value": "application/json" }
            ],
            "url": {
              "raw": "{{baseUrl}}/api/admin/users/{{user_id}}/sessions/kill",
              "host": ["{{baseUrl}}"],
              "path": ["api","admin","users","{{user_id}}","sessions","kill"]
            }
          }
        },
        {
          "name": "Verify User Email",
          "request": {
            "method": "PUT",
            "header": [
              {
                "key": "Authorization",
                "value": "Bearer {{adminToken}}"
              }
            ],
            "url": {
              "raw": "{{baseUrl}}/api/admin/users/{{userId}}/verify-email",
              "host": ["{{baseUrl}}"],
              "path": ["api", "admin", "users", "{{userId}}", "verify-email"]
            }
          }
        },
        {
          "name": "Verify User Mobile",
          "request": {
            "method": "PUT",
            "header": [
              {
                "key": "Authorization",
                "value": "Bearer {{adminToken}}"
              }
            ],
            "url": {
              "raw": "{{baseUrl}}/api/admin/users/{{userId}}/verify-mobile",
              "host": ["{{baseUrl}}"],
              "path": ["api", "admin", "users", "{{userId}}", "verify-mobile"]
            }
          }
        },
        {
          "name": "Get User Login History",
          "request": {
            "method": "GET",
            "header": [
              {
                "key": "Authorization",
                "value": "Bearer {{adminToken}}"
              }
            ],
            "url": {
              "raw": "{{baseUrl}}/api/admin/users/{{userId}}/logins?page=1&limit=10",
              "host": ["{{baseUrl}}"],
              "path": ["api", "admin", "users", "{{userId}}", "logins"],
              "query": [
                {
                  "key": "page",
                  "value": "1"
                },
                {
                  "key": "limit",
                  "value": "10"
                }
              ]
            }
          }
        },
        {
          "name": "Get Audit Logs",
          "request": {
            "method": "GET",
            "header": [
              {
                "key": "Authorization",
                "value": "Bearer {{adminToken}}"
              }
            ],
            "url": {
              "raw": "{{baseUrl}}/api/admin/audit-logs?page=1&limit=10&action=user_login",
              "host": ["{{baseUrl}}"],
              "path": ["api", "admin", "audit-logs"],
              "query": [
                {
                  "key": "page",
                  "value": "1"
                },
                {
                  "key": "limit",
                  "value": "10"
                },
                {
                  "key": "action",
                  "value": "user_login"
                }
              ]
            }
          }
        }
      ]
    },
    {
      "name": "🛡️ Role Management",
      "description": "Manage roles and role-permission assignments. Admin-only.",
      "item": [
        {
          "name": "Create Role",
          "request": {
            "method": "POST",
            "header": [
              {
                "key": "Content-Type",
                "value": "application/json"
              },
              {
                "key": "Authorization",
                "value": "Bearer {{adminToken}}"
              }
            ],
            "body": {
              "mode": "raw",
              "raw": "{\n  \"name\": \"moderator\",\n  \"description\": \"Game moderator with limited admin access\",\n  \"permissions\": [1, 2, 3]\n}"
            },
            "url": {
              "raw": "{{baseUrl}}/api/admin/roles",
              "host": ["{{baseUrl}}"],
              "path": ["api", "admin", "roles"]
            }
          }
        },
        {
          "name": "Get All Roles",
          "request": {
            "method": "GET",
            "header": [
              {
                "key": "Authorization",
                "value": "Bearer {{adminToken}}"
              }
            ],
            "url": {
              "raw": "{{baseUrl}}/api/admin/roles",
              "host": ["{{baseUrl}}"],
              "path": ["api", "admin", "roles"]
            }
          }
        },
        {
          "name": "Update Role",
          "request": {
            "method": "PUT",
            "header": [
              {
                "key": "Content-Type",
                "value": "application/json"
              },
              {
                "key": "Authorization",
                "value": "Bearer {{adminToken}}"
              }
            ],
            "body": {
              "mode": "raw",
              "raw": "{\n  \"description\": \"Updated moderator role with enhanced permissions\",\n  \"isActive\": true\n}"
            },
            "url": {
              "raw": "{{baseUrl}}/api/admin/roles/1",
              "host": ["{{baseUrl}}"],
              "path": ["api", "admin", "roles", "1"]
            }
          }
        },
        {
          "name": "Assign Permissions to Role",
          "request": {
            "method": "POST",
            "header": [
              {
                "key": "Content-Type",
                "value": "application/json"
              },
              {
                "key": "Authorization",
                "value": "Bearer {{adminToken}}"
              }
            ],
            "body": {
              "mode": "raw",
              "raw": "{\n  \"permission_ids\": [1, 2, 3, 4, 5]\n}"
            },
            "url": {
              "raw": "{{baseUrl}}/api/admin/roles/1/permissions",
              "host": ["{{baseUrl}}"],
              "path": ["api", "admin", "roles", "1", "permissions"]
            }
          }
        },
        {
          "name": "Get Role Permissions",
          "request": {
            "method": "GET",
            "header": [
              {
                "key": "Authorization",
                "value": "Bearer {{adminToken}}"
              }
            ],
            "url": {
              "raw": "{{baseUrl}}/api/admin/roles/1/permissions",
              "host": ["{{baseUrl}}"],
              "path": ["api", "admin", "roles", "1", "permissions"]
            }
          }
        },
        {
          "name": "Assign Roles to User",
          "request": {
            "method": "POST",
            "header": [
              {
                "key": "Content-Type",
                "value": "application/json"
              },
              {
                "key": "Authorization",
                "value": "Bearer {{adminToken}}"
              }
            ],
            "body": {
              "mode": "raw",
              "raw": "{\n  \"role_ids\": [1, 2]\n}"
            },
            "url": {
              "raw": "{{baseUrl}}/api/admin/users/{{userId}}/roles",
              "host": ["{{baseUrl}}"],
              "path": ["api", "admin", "users", "{{userId}}", "roles"]
            }
          }
        },
        {
          "name": "Get User Roles",
          "request": {
            "method": "GET",
            "header": [
              {
                "key": "Authorization",
                "value": "Bearer {{adminToken}}"
              }
            ],
            "url": {
              "raw": "{{baseUrl}}/api/admin/users/{{userId}}/roles",
              "host": ["{{baseUrl}}"],
              "path": ["api", "admin", "users", "{{userId}}", "roles"]
            }
          }
        }
      ]
    },
    {
      "name": "🔑 Permission Management",
      "description": "Create and manage permissions used by RBAC. Admin-only.",
      "item": [
        {
          "name": "Create Permission",
          "request": {
            "method": "POST",
            "header": [
              {
                "key": "Content-Type",
                "value": "application/json"
              },
              {
                "key": "Authorization",
                "value": "Bearer {{adminToken}}"
              }
            ],
            "body": {
              "mode": "raw",
              "raw": "{\n  \"name\": \"create_game\",\n  \"description\": \"Create new game sessions\",\n  \"resource\": \"game\",\n  \"action\": \"create\"\n}"
            },
            "url": {
              "raw": "{{baseUrl}}/api/admin/permissions",
              "host": ["{{baseUrl}}"],
              "path": ["api", "admin", "permissions"]
            }
          }
        },
        {
          "name": "Create Multiple Permissions",
          "request": {
            "method": "POST",
            "header": [
              {
                "key": "Content-Type",
                "value": "application/json"
              },
              {
                "key": "Authorization",
                "value": "Bearer {{adminToken}}"
              }
            ],
            "body": {
              "mode": "raw",
              "raw": "{\n  \"name\": \"delete_game\",\n  \"description\": \"Delete game sessions\",\n  \"resource\": \"game\",\n  \"action\": \"delete\"\n}"
            },
            "url": {
              "raw": "{{baseUrl}}/api/admin/permissions",
              "host": ["{{baseUrl}}"],
              "path": ["api", "admin", "permissions"]
            }
          }
        },
        {
          "name": "Get All Permissions",
          "request": {
            "method": "GET",
            "header": [
              {
                "key": "Authorization",
                "value": "Bearer {{adminToken}}"
              }
            ],
            "url": {
              "raw": "{{baseUrl}}/api/admin/permissions",
              "host": ["{{baseUrl}}"],
              "path": ["api", "admin", "permissions"]
            }
          }
        },
        {
          "name": "Update Permission",
          "request": {
            "method": "PUT",
            "header": [
              {
                "key": "Content-Type",
                "value": "application/json"
              },
              {
                "key": "Authorization",
                "value": "Bearer {{adminToken}}"
              }
            ],
            "body": {
              "mode": "raw",
              "raw": "{\n  \"description\": \"Updated permission for game management\",\n  \"isActive\": true\n}"
            },
            "url": {
              "raw": "{{baseUrl}}/api/admin/permissions/1",
              "host": ["{{baseUrl}}"],
              "path": ["api", "admin", "permissions", "1"]
            }
          }
        }
      ]
    },
    {
      "name": "📊 System & Health",
      "description": "System endpoints for health and helper queries.",
      "item": [
        {
          "name": "Health Check",
          "request": {
            "method": "GET",
            "header": [],
            "url": {
              "raw": "{{baseUrl}}/api/health",
              "host": ["{{baseUrl}}"],
              "path": ["api", "health"]
            }
          }
        },
        {
          "name": "Get My Permissions",
          "request": {
            "method": "GET",
            "header": [
              {
                "key": "Authorization",
                "value": "Bearer {{accessToken}}"
              }
            ],
            "url": {
              "raw": "{{baseUrl}}/api/user/permissions",
              "host": ["{{baseUrl}}"],
              "path": ["api", "user", "permissions"]
            }
          }
        }
      ]
    }
  ]
}
